pygme/__init__.py
pygme/__main__.py
pygme/battleship/__init__.py
pygme/battleship/board.py
pygme/battleship/game.py
pygme/battleship/player.py
pygme/battleship/ships.py
pygme/battleship/strategy.py
pygme/data/config.json
pygme/data/dictionary.txt
pygme/game/__init__.py
pygme/game/board.py
pygme/game/game.py
pygme/game/movement.py
pygme/game/player.py
pygme/game/strategy.py
pygme/hangman/__init__.py
pygme/hangman/game.py
pygme/hangman/noose.py
pygme/pong/__init__.py
pygme/snake/__init__.py
pygme/snake/food.py
pygme/snake/game.py
pygme/snake/snake.py
pygme/tictactoe/__init__.py
pygme/utils/__init__.py
pygme/utils/dictionary.py
pygme/utils/display.py
pygme/utils/space.py
pygme/utils/validation.py
pygme-0.3.0.dist-info/METADATA
pygme-0.3.0.dist-info/WHEEL
pygme-0.3.0.dist-info/entry_points.txt
pygme-0.3.0.dist-info/top_level.txt
pygme-0.3.0.dist-info/RECORD
