Metadata-Version: 2.1
Name: pygme
Version: 0.3.0
Summary: Lightweight computer games written in Python
Home-page: https://github.com/adaros92/pygme
License: MIT
Platform: UNKNOWN
Classifier: License :: OSI Approved :: MIT License
Classifier: Programming Language :: Python :: 3
Classifier: Programming Language :: Python :: 3.7
Requires-Python: >=3.6
